TRAPT/CalcSampleRPMatrix.py
TRAPT/CalcTRAUC.py
TRAPT/CalcTRRPMatrix.py
TRAPT/CalcTRSampleRPMatrix.py
TRAPT/DLFS.py
TRAPT/DLVGAE.py
TRAPT/Run.py
TRAPT/Tools.py
TRAPT/__init__.py
TRAPT-0.2.0.dist-info/LICENSE
TRAPT-0.2.0.dist-info/METADATA
TRAPT-0.2.0.dist-info/WHEEL
TRAPT-0.2.0.dist-info/entry_points.txt
TRAPT-0.2.0.dist-info/top_level.txt
TRAPT-0.2.0.dist-info/RECORD
