Metadata-Version: 2.1
Name: TRAPT
Version: 0.2.0
Summary: A multi-stage fused deep learning framework for transcription regulators prediction via integraing large-scale epigenomic data.
Author-email: zhangguorui <mp798378522@gmail.com>
Project-URL: Homepage, https://github.com/TOSTRING-Z/TRAPT
Project-URL: Bug Tracker, https://github.com/TOSTRING-Z/TRAPT/issues
Project-URL: Blog, https://bio.liclab.net/TRAPT
Classifier: Programming Language :: Python :: 3
Classifier: License :: OSI Approved :: MIT License
Classifier: Operating System :: OS Independent
Requires-Python: >=3.7
License-File: LICENSE
Requires-Dist: tqdm
Requires-Dist: numba
Requires-Dist: numpy
Requires-Dist: pandas
Requires-Dist: scikit-learn
Requires-Dist: scipy
Requires-Dist: anndata
Requires-Dist: keras
Requires-Dist: tensorflow
Requires-Dist: torch
